circuit/kadai2/prog/Decoder.v
module SegDecoder(iD,iS,oD);
input [3:0] iD; //0~9の4ビット入力
input iS;
output [7:0] oD;
assign oD = ~DecF(iD);
function [7:0] DecF;
  input [3:0] iD;
  begin
    case(iD)
      4'b0000: DecF = {iS,7'b1000000}; // 0
      4'b0001: DecF = {iS,7'b1111001}; // 1
      4'b0010: DecF = {iS,7'b0100100}; // 2
      4'b0011: DecF = {iS,7'b0110000}; // 3
      4'b0100: DecF = {iS,7'b0011001}; // 4
      4'b0101: DecF = {iS,7'b0010010}; // 5
      4'b0110: DecF = {iS,7'b0000010}; // 6
      4'b0111: DecF = {iS,7'b1111000}; // 7
      4'b1000: DecF = {iS,7'b0000000}; // 8
      4'b1001: DecF = {iS,7'b0010000}; // 9
        default: DecF = 8'b11111111; // 消灯
    endcase
  end
endfunction

endmodule

module Decoder(iA, oF);
  input  [1:0] iA;
  output [3:0] oF;

  function [3:0] Dec;
      input [1:0] iA;
      begin
          case(iA)
          2'b00: Dec = 4'b0001;
          2'b01: Dec = 4'b0010;
          2'b10: Dec = 4'b0100;
          2'b11: Dec = 4'b1000;
          default:Dec = 4'bXXXX;
          endcase
      end
  endfunction
  assign oF = Dec(iA);
endmodule

circuit/kadai2/prog/Selector.v
module Sel(iA,iB,iC,iD,iSw,oOut);
  input [3:0]iA;
  input [3:0]iB;
  input [3:0]iC;
  input [3:0]iD;
  input [1:0]iSw;
  output [3:0]oOut;
  assign oOut = SelF(iA,iB,iC,iD,iSw);
  function [3:0] SelF;
    input [3:0] iA;
    input [3:0] iB;
    input [3:0] iC;
    input [3:0] iD;
    input [1:0] iSw;
  begin
    case(iSw)
        2'b00: SelF = iA;
        2'b01: SelF = iB;
        2'b10: SelF = iC;
        2'b11: SelF = iD;
      default: SelF=4'bXXXX;
    endcase
  end
  endfunction
endmodule

circuit/kadai2/prog/Counter100.v
module Counter(iClk,iRst,iStop,iP,oCnt1,oCnt2,oCnt3,oCnt4);
    input iClk;
    input iRst;
    input iStop;
    input [1:0] iP;
    output [3:0] oCnt1;
    output [3:0] oCnt2;
    output [3:0] oCnt3;
    output [3:0] oCnt4;
    reg [3:0] cnt1 = 4'd0;
    reg [3:0] cnt2 = 4'd0;
    reg [3:0] cnt3 = 4'd0;
    reg [3:0] cnt4 = 4'd0;
    reg [3:0] cnt5 = 4'd0;
    reg [3:0] cnt6 = 4'd0;
    reg [3:0] cnt7 = 4'd0;
    reg [3:0] cnt8 = 4'd0;

    assign oCnt1 = iP == 2'b00 ? cnt4 :
                   iP == 2'b01 ? cnt3 :
                   iP == 2'b10 ? cnt2 : cnt1;
    assign oCnt2 = iP == 2'b00 ? cnt5 :
                   iP == 2'b01 ? cnt4 :
                   iP == 2'b10 ? cnt3 : cnt2;
    assign oCnt3 = iP == 2'b00 ? cnt6 :
                   iP == 2'b01 ? cnt5 :
                   iP == 2'b10 ? cnt4 : cnt3;
    assign oCnt4 = iP == 2'b00 ? cnt7 :
                   iP == 2'b01 ? cnt6 :
                   iP == 2'b10 ? cnt5 : cnt4;

    always @(posedge iClk) begin
        if (~iRst) begin
            cnt1 <= 4'd0;
            cnt2 <= 4'd0;
            cnt3 <= 4'd0;
            cnt4 <= 4'd0;
            cnt5 <= 4'd0;
            cnt6 <= 4'd0;
            cnt7 <= 4'd0;
            cnt8 <= 4'd0;
        end
        else if (iStop) begin
            cnt1 <= cnt1;
            cnt2 <= cnt2;
            cnt3 <= cnt3;
            cnt4 <= cnt4;
            cnt5 <= cnt5;
            cnt6 <= cnt6;
            cnt7 <= cnt7;
            cnt8 <= cnt8;
        end else if (cnt1 == 4'd9) begin
            cnt1 <= 4'd0;
            if (cnt2 == 4'd9) begin
                cnt2 <= 4'd0;
                if (cnt3 == 4'd9) begin
                    cnt3 <= 4'd0;
                    if (cnt4 == 4'd9) begin
                        cnt4 <= 4'd0;
                        if (cnt5 == 4'd9) begin
                            cnt5 <= 4'd0;
                            if (cnt6 == 4'd9) begin
                                cnt6 <= 4'd0;
                                if (cnt7 == 4'd9) begin
                                    cnt7 <= 4'd0;
                                    if (cnt8 == 4'd9) begin
                                        cnt8 <= 4'd0;
                                    end
                                    else begin
                                        cnt8 <=cnt8 + 4'd1;
                                    end
                                end
                                else begin
                                    cnt7 <=cnt7 + 4'd1;
                                end
                            end
                            else begin
                                cnt6 <=cnt6 + 4'd1;
                            end
                        end
                        else begin
                            cnt5 <=cnt5 + 4'd1;
                        end
                    end
                    else begin
                        cnt4 <=cnt4 + 4'd1;
                    end
                end
                else begin
                    cnt3 <=cnt3 + 4'd1;
                end
            end
            else begin
                cnt2 <=cnt2 + 4'd1;
            end
        end
        else begin
           cnt1 <=cnt1 + 4'd1;
        end
    end
    
endmodule

module DeCounter(iClk,iRst,iStop,iP,oCnt1,oCnt2,oCnt3,oCnt4);
    input iClk;
    input iRst;
    input iStop;
    input [1:0] iP;
    output [3:0] oCnt1;
    output [3:0] oCnt2;
    output [3:0] oCnt3;
    output [3:0] oCnt4;
    reg [3:0] cnt1 = 4'd0;
    reg [3:0] cnt2 = 4'd0;
    reg [3:0] cnt3 = 4'd0;
    reg [3:0] cnt4 = 4'd0;
    reg [3:0] cnt5 = 4'd0;
    reg [3:0] cnt6 = 4'd0;
    reg [3:0] cnt7 = 4'd0;
    reg [3:0] cnt8 = 4'd0;

    assign oCnt1 = iP == 2'b00 ? cnt4 :
                   iP == 2'b01 ? cnt3 :
                   iP == 2'b10 ? cnt2 : cnt1;
    assign oCnt2 = iP == 2'b00 ? cnt5 :
                   iP == 2'b01 ? cnt4 :
                   iP == 2'b10 ? cnt3 : cnt2;
    assign oCnt3 = iP == 2'b00 ? cnt6 :
                   iP == 2'b01 ? cnt5 :
                   iP == 2'b10 ? cnt4 : cnt3;
    assign oCnt4 = iP == 2'b00 ? cnt7 :
                   iP == 2'b01 ? cnt6 :
                   iP == 2'b10 ? cnt5 : cnt4;

    always @(posedge iClk) begin
        if (~iRst) begin
            cnt1 <= 4'd0;
            cnt2 <= 4'd0;
            cnt3 <= 4'd0;
            cnt4 <= 4'd0;
            cnt5 <= 4'd0;
            cnt6 <= 4'd0;
            cnt7 <= 4'd0;
            cnt8 <= 4'd0;
        end
        else if (iStop) begin
            cnt1 <= cnt1;
            cnt2 <= cnt2;
            cnt3 <= cnt3;
            cnt4 <= cnt4;
            cnt5 <= cnt5;
            cnt6 <= cnt6;
            cnt7 <= cnt7;
            cnt8 <= cnt8;
        end else  if (cnt1 == 4'd0) begin
            cnt1 <= 4'd9;
            if (cnt2 == 4'd0) begin
                cnt2 <= 4'd9;
                if (cnt3 == 4'd0) begin
                    cnt3 <= 4'd9;
                    if (cnt4 == 4'd0) begin
                        cnt4 <= 4'd9;
                        if (cnt5 == 4'd0) begin
                            cnt5 <= 4'd9;
                            if (cnt6 == 4'd0) begin
                                cnt6 <= 4'd9;
                                if (cnt7 == 4'd0) begin
                                    cnt7 <= 4'd9;
                                    if (cnt8 == 4'd0) begin
                                        cnt8 <= 4'd9;
                                    end
                                    else begin
                                        cnt8 <=cnt8 - 4'd1;
                                    end
                                end
                                else begin
                                    cnt7 <=cnt7 - 4'd1;
                                end
                            end
                            else begin
                                cnt6 <=cnt6 - 4'd1;
                            end
                        end
                        else begin
                            cnt5 <=cnt5 - 4'd1;
                        end
                    end
                    else begin
                        cnt4 <=cnt4 - 4'd1;
                    end
                end
                else begin
                    cnt3 <=cnt3 - 4'd1;
                end
            end
            else begin
                cnt2 <=cnt2 - 4'd1;
            end
        end
        else begin
           cnt1 <=cnt1 - 4'd1;
        end
    end
    
endmodule

module Count4sw(iClk, oSw);
    input iClk;
    output reg [1:0] oSw = 2'b00;

    always @(posedge iClk) begin
        if (oSw == 2'b11) begin
            oSw <= 2'b00;
        end
        else begin
            oSw <= oSw + 2'b01;
        end
    end
endmodule

circuit/kadai2/prog/divider.v
// 27MHz を 1Hz に分周するクロック分周器
// module d4c(iClk, oClk);
// 	input iClk; /* 27[MHz] */
// 	output oClk; /* 1[Hz] */
// 	reg [23:0] dd = 24'd1349; // 24ビットカウンタ
// 	reg oClk = 1'b0;
	
// 	always @(posedge iClk) begin
// 		if(dd == 24'd1349) begin // 13,500,000 - 1
// 			oClk <= ~oClk; // 出力クロックを反転
// 			dd <= 24'd0;   // カウンタリセット
// 		end
// 		else begin
// 			dd <= dd + 24'd1; // カウンタインクリメント
// 		end
// 	end
// endmodule

module d4dl(iClk, oClk);
	input iClk; /* 27[MHz] */
	output oClk; /* 1[kHz] */
	reg [14:0] dd = 15'd13499;  //14ビットカウンタ
	reg oClk = 1'b0;
	
	always @(posedge iClk) begin
		if(dd == 15'd13499) begin //13,500 - 1
			oClk <= ~oClk;  //出力クロックを反転
			dd <= 15'd0;    //カウンタリセット
		end
		else begin
			dd <= dd + 15'd1;  //カウンタインクリメント
		end
	end
endmodule

circuit/kadai2/prog/main.v
module MAIN(iClk,iPoint,iM,iStop,iRst,oD,oD1,oD2,oD3,oD4);
    input iClk; // 27MHz クロック入力
    input iPoint;
    input iM;
    input iRst;
    input iStop;
    output [7:0] oD;
    output oD1;
    output oD2;
    output oD3;
    output oD4;

    
    // wire w1Hz;
    wire w1kHz;
    // wire wd1kHz;`
    wire [3:0] wcnt1;
    wire [3:0] wcnt2;
    wire [3:0] wcnt3;
    wire [3:0] wcnt4;
    wire [3:0] wcnt11;
    wire [3:0] wcnt21;
    wire [3:0] wcnt31;
    wire [3:0] wcnt41;
    wire [3:0] wcnt12;
    wire [3:0] wcnt22;
    wire [3:0] wcnt32;
    wire [3:0] wcnt42;

    wire [3:0] wcnt;
    wire [1:0] wsw;
    wire [1:0] wsp;
    wire ws;
    assign ws = (wsw == wsp )? 1'b0 : 1'b1;

    // d4c u1(.iClk(iClk), .oClk(w1Hz));
    d4dl u2(.iClk(iClk), .oClk(w1kHz));
    Count4sw usw(.iClk(w1kHz), .oSw(wsw));
    Count4sw usw2(.iClk(iPoint), .oSw(wsp));
    Counter u3(.iClk(w1kHz), .iRst(iRst),.iStop(~iStop), .iP(wsp),.oCnt1(wcnt11), .oCnt2(wcnt21), .oCnt3(wcnt31), .oCnt4(wcnt41));
    DeCounter u3d(.iClk(w1kHz), .iRst(iRst), .iStop(~iStop),.iP(wsp),.oCnt1(wcnt12), .oCnt2(wcnt22), .oCnt3(wcnt32), .oCnt4(wcnt42));
    assign wcnt1 = iM == 1'b0 ? wcnt11 : wcnt12;
    assign wcnt2 = iM == 1'b0 ? wcnt21 : wcnt22;
    assign wcnt3 = iM == 1'b0 ? wcnt31 : wcnt32;
    assign wcnt4 = iM == 1'b0 ? wcnt41 : wcnt42;
    Sel u4(.iA(wcnt1), .iB(wcnt2),.iC(wcnt3),.iD(wcnt4), .iSw(wsw), .oOut(wcnt));
    SegDecoder u5(.iD(wcnt),.iS(ws), .oD(oD));
    Decoder u6(.iA(wsw), .oF({oD4,oD3,oD2,oD1}));
endmodule

circuit/kadai2/prog/tb.v

`timescale 10ns / 1ps
module MAINTEST;

reg iClk = 0;
reg iRst = 0;
reg iPoint = 0;
reg iM = 0;
reg iStop = 0;

wire [7:0] oD;
wire oD1;
wire oD2;
wire oD3;
wire oD4;

MAIN main_inst(
    iClk,
    iPoint,
    iM,
    iStop,
    iRst,
    oD,
    oD1,
    oD2,
    oD3,
    oD4
);

// クロック生成（500MHz）
always #1 iClk = ~iClk;

initial begin
    // 初期化
    iClk   = 0;
    iRst   = 1;
    iPoint = 0;
    iM     = 0;
    iStop  = 0;

    // 波形ダンプ
    $dumpfile("main.vcd");
    $dumpvars(0, MAINTEST);
    #1  iRst = 1;
//     #1 iM=1;
    #1 iStop = 0;
    #1 iPoint = 1;
    #1 iPoint = 0;
    #1 iPoint = 1;
    #1 iPoint = 0;
    #1 iPoint = 1;
    #1 iPoint = 0;
    #1 iStop = 1;
    #1000;

    $finish;
end

endmodule

circuit/kadai2/prog/main.vcd
$date
	Tue Jan 06 03:23:18 2026
$end
$version
	Icarus Verilog
$end
$timescale
	1ps
$end
$scope module MAINTEST $end
$var wire 1 ! oD4 $end
$var wire 1 " oD3 $end
$var wire 1 # oD2 $end
$var wire 1 $ oD1 $end
$var wire 8 % oD [7:0] $end
$var reg 1 & iClk $end
$var reg 1 ' iM $end
$var reg 1 ( iPoint $end
$var reg 1 ) iRst $end
$var reg 1 * iStop $end
$scope module main_inst $end
$var wire 1 & iClk $end
$var wire 1 ' iM $end
$var wire 1 ( iPoint $end
$var wire 1 ) iRst $end
$var wire 1 * iStop $end
$var wire 2 + wsw [1:0] $end
$var wire 2 , wsp [1:0] $end
$var wire 1 - ws $end
$var wire 4 . wcnt42 [3:0] $end
$var wire 4 / wcnt41 [3:0] $end
$var wire 4 0 wcnt4 [3:0] $end
$var wire 4 1 wcnt32 [3:0] $end
$var wire 4 2 wcnt31 [3:0] $end
$var wire 4 3 wcnt3 [3:0] $end
$var wire 4 4 wcnt22 [3:0] $end
$var wire 4 5 wcnt21 [3:0] $end
$var wire 4 6 wcnt2 [3:0] $end
$var wire 4 7 wcnt12 [3:0] $end
$var wire 4 8 wcnt11 [3:0] $end
$var wire 4 9 wcnt1 [3:0] $end
$var wire 4 : wcnt [3:0] $end
$var wire 1 ; w1kHz $end
$var wire 1 ! oD4 $end
$var wire 1 " oD3 $end
$var wire 1 # oD2 $end
$var wire 1 $ oD1 $end
$var wire 8 < oD [7:0] $end
$scope module u2 $end
$var wire 1 & iClk $end
$var reg 15 = dd [14:0] $end
$var reg 1 ; oClk $end
$upscope $end
$scope module u3 $end
$var wire 1 & iClk $end
$var wire 1 ) iRst $end
$var wire 1 > iStop $end
$var wire 4 ? oCnt4 [3:0] $end
$var wire 4 @ oCnt3 [3:0] $end
$var wire 4 A oCnt2 [3:0] $end
$var wire 4 B oCnt1 [3:0] $end
$var wire 2 C iP [1:0] $end
$var reg 4 D cnt1 [3:0] $end
$var reg 4 E cnt2 [3:0] $end
$var reg 4 F cnt3 [3:0] $end
$var reg 4 G cnt4 [3:0] $end
$var reg 4 H cnt5 [3:0] $end
$var reg 4 I cnt6 [3:0] $end
$var reg 4 J cnt7 [3:0] $end
$var reg 4 K cnt8 [3:0] $end
$upscope $end
$scope module u3d $end
$var wire 1 & iClk $end
$var wire 1 ) iRst $end
$var wire 1 L iStop $end
$var wire 4 M oCnt4 [3:0] $end
$var wire 4 N oCnt3 [3:0] $end
$var wire 4 O oCnt2 [3:0] $end
$var wire 4 P oCnt1 [3:0] $end
$var wire 2 Q iP [1:0] $end
$var reg 4 R cnt1 [3:0] $end
$var reg 4 S cnt2 [3:0] $end
$var reg 4 T cnt3 [3:0] $end
$var reg 4 U cnt4 [3:0] $end
$var reg 4 V cnt5 [3:0] $end
$var reg 4 W cnt6 [3:0] $end
$var reg 4 X cnt7 [3:0] $end
$var reg 4 Y cnt8 [3:0] $end
$upscope $end
$scope module u4 $end
$var wire 4 Z iA [3:0] $end
$var wire 4 [ iB [3:0] $end
$var wire 4 \ iC [3:0] $end
$var wire 4 ] iD [3:0] $end
$var wire 4 ^ oOut [3:0] $end
$var wire 2 _ iSw [1:0] $end
$scope function SelF $end
$var reg 4 ` iA [3:0] $end
$var reg 4 a iB [3:0] $end
$var reg 4 b iC [3:0] $end
$var reg 4 c iD [3:0] $end
$var reg 2 d iSw [1:0] $end
$upscope $end
$upscope $end
$scope module u5 $end
$var wire 4 e iD [3:0] $end
$var wire 1 - iS $end
$var wire 8 f oD [7:0] $end
$scope function DecF $end
$var reg 4 g iD [3:0] $end
$upscope $end
$upscope $end
$scope module u6 $end
$var wire 4 h oF [3:0] $end
$var wire 2 i iA [1:0] $end
$scope function Dec $end
$var reg 2 j iA [1:0] $end
$upscope $end
$upscope $end
$scope module usw $end
$var wire 1 & iClk $end
$var reg 2 k oSw [1:0] $end
$upscope $end
$scope module usw2 $end
$var wire 1 ( iClk $end
$var reg 2 l oSw [1:0] $end
$upscope $end
$upscope $end
$upscope $end
$enddefinitions $end
$comment Show the parameter values. $end
$dumpall
$end
#0
$dumpvars
b0 l
b0 k
b0 j
b0 i
b1 h
b0 g
b10111111 f
b0 e
b0 d
b0 c
b0 b
b0 a
b0 `
b0 _
b0 ^
b0 ]
b0 \
b0 [
b0 Z
b0 Y
b0 X
b0 W
b0 V
b0 U
b0 T
b0 S
b0 R
b0 Q
b0 P
b0 O
b0 N
b0 M
1L
b0 K
b0 J
b0 I
b0 H
b0 G
b0 F
b0 E
b0 D
b0 C
b0 B
b0 A
b0 @
b0 ?
1>
b11010010111011 =
b10111111 <
0;
b0 :
b0 9
b0 8
b0 7
b0 6
b0 5
b0 4
b0 3
b0 2
b0 1
b0 0
b0 /
b0 .
0-
b0 ,
b0 +
0*
1)
0(
0'
0&
b10111111 %
1$
0#
0"
0!
$end
#10000
0$
1#
b10 h
b1 j
b1 d
1-
b0 =
1;
b1 +
b1 _
b1 i
b1 k
1&
#20000
1'
0&
#30000
0#
1"
b100 h
b10 j
b10 d
b10 +
b10 _
b10 i
b10 k
b1 =
1&
#40000
b1 ,
b1 C
b1 Q
b1 l
1(
0&
#50000
0"
1!
b1000 h
b11 j
b11 d
b10 =
b11 +
b11 _
b11 i
b11 k
0(
1&
#60000
b10 ,
b10 C
b10 Q
b10 l
1(
0&
#70000
1$
0!
b1 h
b0 j
b0 d
b0 +
b0 _
b0 i
b0 k
b11 =
0(
1&
#80000
b11 ,
b11 C
b11 Q
b11 l
1(
0&
#90000
0$
1#
b10 h
b1 j
b1 d
b100 =
b1 +
b1 _
b1 i
b1 k
0(
1&
#100000
0>
0L
1*
0&
#110000
b1101111 %
b1101111 <
b1101111 f
b1001 g
b1001 :
b1001 ^
b1001 e
b1001 c
b1001 b
b1001 a
b1001 `
b1001 0
b1001 ]
b1001 3
b1001 \
b1001 6
b1001 [
b1001 9
b1001 Z
b1001 .
b1001 M
b1001 1
b1001 N
b1001 4
b1001 O
b1001 7
b1001 P
b1 8
b1 B
0#
1"
b100 h
b10 j
b10 d
b1001 Y
b1001 X
b1001 W
b1001 V
b1001 U
b1001 T
b1001 S
b1001 R
b1 D
b10 +
b10 _
b10 i
b10 k
b101 =
1&
#120000
0&
#130000
b1000 `
b1000 9
b1000 Z
b10 8
b10 B
b1000 7
b1000 P
0"
1!
b1000 h
b11 j
b11 d
0-
b110 =
b11 +
b11 _
b11 i
b11 k
b10 D
b1000 R
1&
#140000
0&
#150000
b111 `
b111 9
b111 Z
b111 7
b111 P
b11 8
b11 B
b111 %
b111 <
b111 f
1$
0!
b111 g
b1 h
b0 j
b111 :
b111 ^
b111 e
b0 d
1-
b111 R
b11 D
b0 +
b0 _
b0 i
b0 k
b111 =
1&
#160000
0&
#170000
b110 `
b110 9
b110 Z
b1101111 %
b1101111 <
b1101111 f
b100 8
b100 B
b110 7
b110 P
0$
1#
b1001 g
b10 h
b1 j
b1001 :
b1001 ^
b1001 e
b1 d
b1000 =
b1 +
b1 _
b1 i
b1 k
b100 D
b110 R
1&
#180000
0&
#190000
b101 `
b101 9
b101 Z
b101 7
b101 P
b101 8
b101 B
0#
1"
b100 h
b10 j
b10 d
b101 R
b101 D
b10 +
b10 _
b10 i
b10 k
b1001 =
1&
#200000
0&
#210000
b100 `
b100 9
b100 Z
b110 8
b110 B
b100 7
b100 P
0"
1!
b1000 h
b11 j
b11 d
0-
b1010 =
b11 +
b11 _
b11 i
b11 k
b110 D
b100 R
1&
#220000
0&
#230000
b11 `
b11 9
b11 Z
b11 7
b11 P
b111 8
b111 B
b1001111 %
b1001111 <
b1001111 f
1$
0!
b11 g
b1 h
b0 j
b11 :
b11 ^
b11 e
b0 d
1-
b11 R
b111 D
b0 +
b0 _
b0 i
b0 k
b1011 =
1&
#240000
0&
#250000
b10 `
b10 9
b10 Z
b1101111 %
b1101111 <
b1101111 f
b1000 8
b1000 B
b10 7
b10 P
0$
1#
b1001 g
b10 h
b1 j
b1001 :
b1001 ^
b1001 e
b1 d
b1100 =
b1 +
b1 _
b1 i
b1 k
b1000 D
b10 R
1&
#260000
0&
#270000
b1 `
b1 9
b1 Z
b1 7
b1 P
b1001 8
b1001 B
0#
1"
b100 h
b10 j
b10 d
b1 R
b1001 D
b10 +
b10 _
b10 i
b10 k
b1101 =
1&
#280000
0&
#290000
b0 `
b0 9
b0 Z
b1 5
b1 A
b0 8
b0 B
b0 7
b0 P
0"
1!
b1000 h
b11 j
b11 d
0-
b1110 =
b11 +
b11 _
b11 i
b11 k
b1 E
b0 D
b0 R
1&
#300000
0&
#310000
b1000 a
b1001 `
b1000 6
b1000 [
b1001 9
b1001 Z
b1000 4
b1000 O
b1001 7
b1001 P
b1 8
b1 B
b1101111 %
b1101111 <
b1101111 f
1$
0!
b1001 g
b1 h
b0 j
b1001 :
b1001 ^
b1001 e
b0 d
1-
b1000 S
b1001 R
b1 D
b0 +
b0 _
b0 i
b0 k
b1111 =
1&
#320000
0&
#330000
b1000 `
b1000 9
b1000 Z
b1111111 %
b1111111 <
b1111111 f
b10 8
b10 B
b1000 7
b1000 P
0$
1#
b1000 g
b10 h
b1 j
b1000 :
b1000 ^
b1000 e
b1 d
b10000 =
b1 +
b1 _
b1 i
b1 k
b10 D
b1000 R
1&
#340000
0&
#350000
b111 `
b111 9
b111 Z
b111 7
b111 P
b11 8
b11 B
b1101111 %
b1101111 <
b1101111 f
0#
1"
b1001 g
b100 h
b10 j
b1001 :
b1001 ^
b1001 e
b10 d
b111 R
b11 D
b10 +
b10 _
b10 i
b10 k
b10001 =
1&
#360000
0&
#370000
b110 `
b110 9
b110 Z
b100 8
b100 B
b110 7
b110 P
0"
1!
b1000 h
b11 j
b11 d
0-
b10010 =
b11 +
b11 _
b11 i
b11 k
b100 D
b110 R
1&
#380000
0&
#390000
b101 `
b101 9
b101 Z
b101 7
b101 P
b101 8
b101 B
b1101101 %
b1101101 <
b1101101 f
1$
0!
b101 g
b1 h
b0 j
b101 :
b101 ^
b101 e
b0 d
1-
b101 R
b101 D
b0 +
b0 _
b0 i
b0 k
b10011 =
1&
#400000
0&
#410000
b100 `
b100 9
b100 Z
b1111111 %
b1111111 <
b1111111 f
b110 8
b110 B
b100 7
b100 P
0$
1#
b1000 g
b10 h
b1 j
b1000 :
b1000 ^
b1000 e
b1 d
b10100 =
b1 +
b1 _
b1 i
b1 k
b110 D
b100 R
1&
#420000
0&
#430000
b11 `
b11 9
b11 Z
b11 7
b11 P
b111 8
b111 B
b1101111 %
b1101111 <
b1101111 f
0#
1"
b1001 g
b100 h
b10 j
b1001 :
b1001 ^
b1001 e
b10 d
b11 R
b111 D
b10 +
b10 _
b10 i
b10 k
b10101 =
1&
#440000
0&
#450000
b10 `
b10 9
b10 Z
b1000 8
b1000 B
b10 7
b10 P
0"
1!
b1000 h
b11 j
b11 d
0-
b10110 =
b11 +
b11 _
b11 i
b11 k
b1000 D
b10 R
1&
#460000
0&
#470000
b1 `
b1 9
b1 Z
b1 7
b1 P
b1001 8
b1001 B
b110 %
b110 <
b110 f
1$
0!
b1 g
b1 h
b0 j
b1 :
b1 ^
b1 e
b0 d
1-
b1 R
b1001 D
b0 +
b0 _
b0 i
b0 k
b10111 =
1&
#480000
0&
#490000
b0 `
b0 9
b0 Z
b1111111 %
b1111111 <
b1111111 f
b10 5
b10 A
b0 8
b0 B
b0 7
b0 P
0$
1#
b1000 g
b10 h
b1 j
b1000 :
b1000 ^
b1000 e
b1 d
b11000 =
b1 +
b1 _
b1 i
b1 k
b10 E
b0 D
b0 R
1&
#500000
0&
#510000
b111 a
b1001 `
b111 6
b111 [
b1001 9
b1001 Z
b111 4
b111 O
b1001 7
b1001 P
b1 8
b1 B
b1101111 %
b1101111 <
b1101111 f
0#
1"
b1001 g
b100 h
b10 j
b1001 :
b1001 ^
b1001 e
b10 d
b111 S
b1001 R
b1 D
b10 +
b10 _
b10 i
b10 k
b11001 =
1&
#520000
0&
#530000
b1000 `
b1000 9
b1000 Z
b10 8
b10 B
b1000 7
b1000 P
0"
1!
b1000 h
b11 j
b11 d
0-
b11010 =
b11 +
b11 _
b11 i
b11 k
b10 D
b1000 R
1&
#540000
0&
#550000
b111 `
b111 9
b111 Z
b111 7
b111 P
b11 8
b11 B
b111 %
b111 <
b111 f
1$
0!
b111 g
b1 h
b0 j
b111 :
b111 ^
b111 e
b0 d
1-
b111 R
b11 D
b0 +
b0 _
b0 i
b0 k
b11011 =
1&
#560000
0&
#570000
b110 `
b110 9
b110 Z
b100 8
b100 B
b110 7
b110 P
0$
1#
b10 h
b1 j
b1 d
b11100 =
b1 +
b1 _
b1 i
b1 k
b100 D
b110 R
1&
#580000
0&
#590000
b101 `
b101 9
b101 Z
b101 7
b101 P
b101 8
b101 B
b1101111 %
b1101111 <
b1101111 f
0#
1"
b1001 g
b100 h
b10 j
b1001 :
b1001 ^
b1001 e
b10 d
b101 R
b101 D
b10 +
b10 _
b10 i
b10 k
b11101 =
1&
#600000
0&
#610000
b100 `
b100 9
b100 Z
b110 8
b110 B
b100 7
b100 P
0"
1!
b1000 h
b11 j
b11 d
0-
b11110 =
b11 +
b11 _
b11 i
b11 k
b110 D
b100 R
1&
#620000
0&
#630000
b11 `
b11 9
b11 Z
b11 7
b11 P
b111 8
b111 B
b1001111 %
b1001111 <
b1001111 f
1$
0!
b11 g
b1 h
b0 j
b11 :
b11 ^
b11 e
b0 d
1-
b11 R
b111 D
b0 +
b0 _
b0 i
b0 k
b11111 =
1&
#640000
0&
#650000
b10 `
b10 9
b10 Z
b111 %
b111 <
b111 f
b1000 8
b1000 B
b10 7
b10 P
0$
1#
b111 g
b10 h
b1 j
b111 :
b111 ^
b111 e
b1 d
b100000 =
b1 +
b1 _
b1 i
b1 k
b1000 D
b10 R
1&
#660000
0&
#670000
b1 `
b1 9
b1 Z
b1 7
b1 P
b1001 8
b1001 B
b1101111 %
b1101111 <
b1101111 f
0#
1"
b1001 g
b100 h
b10 j
b1001 :
b1001 ^
b1001 e
b10 d
b1 R
b1001 D
b10 +
b10 _
b10 i
b10 k
b100001 =
1&
#680000
0&
#690000
b0 `
b0 9
b0 Z
b11 5
b11 A
b0 8
b0 B
b0 7
b0 P
0"
1!
b1000 h
b11 j
b11 d
0-
b100010 =
b11 +
b11 _
b11 i
b11 k
b11 E
b0 D
b0 R
1&
#700000
0&
#710000
b110 a
b1001 `
b110 6
b110 [
b1001 9
b1001 Z
b110 4
b110 O
b1001 7
b1001 P
b1 8
b1 B
b1101111 %
b1101111 <
b1101111 f
1$
0!
b1001 g
b1 h
b0 j
b1001 :
b1001 ^
b1001 e
b0 d
1-
b110 S
b1001 R
b1 D
b0 +
b0 _
b0 i
b0 k
b100011 =
1&
#720000
0&
#730000
b1000 `
b1000 9
b1000 Z
b1111101 %
b1111101 <
b1111101 f
b10 8
b10 B
b1000 7
b1000 P
0$
1#
b110 g
b10 h
b1 j
b110 :
b110 ^
b110 e
b1 d
b100100 =
b1 +
b1 _
b1 i
b1 k
b10 D
b1000 R
1&
#740000
0&
#750000
b111 `
b111 9
b111 Z
b111 7
b111 P
b11 8
b11 B
b1101111 %
b1101111 <
b1101111 f
0#
1"
b1001 g
b100 h
b10 j
b1001 :
b1001 ^
b1001 e
b10 d
b111 R
b11 D
b10 +
b10 _
b10 i
b10 k
b100101 =
1&
#760000
0&
#770000
b110 `
b110 9
b110 Z
b100 8
b100 B
b110 7
b110 P
0"
1!
b1000 h
b11 j
b11 d
0-
b100110 =
b11 +
b11 _
b11 i
b11 k
b100 D
b110 R
1&
#780000
0&
#790000
b101 `
b101 9
b101 Z
b101 7
b101 P
b101 8
b101 B
b1101101 %
b1101101 <
b1101101 f
1$
0!
b101 g
b1 h
b0 j
b101 :
b101 ^
b101 e
b0 d
1-
b101 R
b101 D
b0 +
b0 _
b0 i
b0 k
b100111 =
1&
#800000
0&
#810000
b100 `
b100 9
b100 Z
b1111101 %
b1111101 <
b1111101 f
b110 8
b110 B
b100 7
b100 P
0$
1#
b110 g
b10 h
b1 j
b110 :
b110 ^
b110 e
b1 d
b101000 =
b1 +
b1 _
b1 i
b1 k
b110 D
b100 R
1&
#820000
0&
#830000
b11 `
b11 9
b11 Z
b11 7
b11 P
b111 8
b111 B
b1101111 %
b1101111 <
b1101111 f
0#
1"
b1001 g
b100 h
b10 j
b1001 :
b1001 ^
b1001 e
b10 d
b11 R
b111 D
b10 +
b10 _
b10 i
b10 k
b101001 =
1&
#840000
0&
#850000
b10 `
b10 9
b10 Z
b1000 8
b1000 B
b10 7
b10 P
0"
1!
b1000 h
b11 j
b11 d
0-
b101010 =
b11 +
b11 _
b11 i
b11 k
b1000 D
b10 R
1&
#860000
0&
#870000
b1 `
b1 9
b1 Z
b1 7
b1 P
b1001 8
b1001 B
b110 %
b110 <
b110 f
1$
0!
b1 g
b1 h
b0 j
b1 :
b1 ^
b1 e
b0 d
1-
b1 R
b1001 D
b0 +
b0 _
b0 i
b0 k
b101011 =
1&
#880000
0&
#890000
b0 `
b0 9
b0 Z
b1111101 %
b1111101 <
b1111101 f
b100 5
b100 A
b0 8
b0 B
b0 7
b0 P
0$
1#
b110 g
b10 h
b1 j
b110 :
b110 ^
b110 e
b1 d
b101100 =
b1 +
b1 _
b1 i
b1 k
b100 E
b0 D
b0 R
1&
#900000
0&
#910000
b101 a
b1001 `
b101 6
b101 [
b1001 9
b1001 Z
b101 4
b101 O
b1001 7
b1001 P
b1 8
b1 B
b1101111 %
b1101111 <
b1101111 f
0#
1"
b1001 g
b100 h
b10 j
b1001 :
b1001 ^
b1001 e
b10 d
b101 S
b1001 R
b1 D
b10 +
b10 _
b10 i
b10 k
b101101 =
1&
#920000
0&
